{
  "convocatoriaId": "diputacion-toledo-administrativo-c1-2026",
  "actualizadoEl": "2026-07-22",
  "situacionPersonal": {
    "inscrito": true,
    "estado": "Solicitud presentada dentro del plazo",
    "convocatoria": "2 plazas · Administrativo C1 · oposición libre",
    "notaPrivacidad": "El justificante, la solicitud y el resto de documentación personal se conservan fuera del repositorio público."
  },
  "plazoSolicitudes": {
    "desde": "2026-07-06",
    "hasta": "2026-07-31",
    "estado": "ABIERTO"
  },
  "siguienteHito": "Lista provisional de personas admitidas y excluidas",
  "ultimaComprobacion": "No consta todavía lista provisional publicada en el portal oficial de la Diputación de Toledo."
}
